cartinize/__init__.py
cartinize/carti.py
cartinize/cartijoin.py
cartinize/cartinize.py
cartinize/leet.py
cartinize/main.py
cartinize/assets/carti_fillers.json
cartinize/assets/leet_dict.json
cartinize-1.dist-info/METADATA
cartinize-1.dist-info/WHEEL
cartinize-1.dist-info/top_level.txt
cartinize-1.dist-info/RECORD
