Metadata-Version: 2.1
Name: cartinize
Version: 1
Summary: Cartinese translator
Author: ktkv419 (Kutikov Pasha)
Author-email: <kutikovpasha@gmail.com>
Keywords: python,string,translate,carti,slatt
